modelcaller/__init__.py
modelcaller/mc.py
modelcaller/modelcaller.py
modelcaller-0.1.data/data/LICENSE.txt
modelcaller-0.1.dist-info/LICENSE.txt
modelcaller-0.1.dist-info/METADATA
modelcaller-0.1.dist-info/WHEEL
modelcaller-0.1.dist-info/top_level.txt
modelcaller-0.1.dist-info/RECORD
