Metadata-Version: 2.1
Name: modelcaller
Version: 0.1
Summary: ModelCaller for AI
Home-page: https://github.com/mukdal/modelcaller
Author: Mukesh Dalal
Author-email: mukesh@aidaa.ai
License: Custom
Keywords: modelcaller artficial intelligence machine learning ml ai systems transformation model
Classifier: Development Status :: 3 - Alpha
Classifier: Intended Audience :: Developers
Classifier: License :: Free for non-commercial use
Classifier: Operating System :: OS Independent
Classifier: Topic :: Software Development :: Libraries
Classifier: Programming Language :: Python :: 3
Classifier: Programming Language :: Python :: 3.12
Requires-Python: >=3.9
License-File: LICENSE.txt
Requires-Dist: requests
Requires-Dist: numpy
Requires-Dist: scikit-learn
Requires-Dist: torch
